neural_renderer_paddle/__init__.py
neural_renderer_paddle/get_points_from_angles.py
neural_renderer_paddle/lighting.py
neural_renderer_paddle/load_obj.py
neural_renderer_paddle/look.py
neural_renderer_paddle/look_at.py
neural_renderer_paddle/mesh.py
neural_renderer_paddle/perspective.py
neural_renderer_paddle/projection.py
neural_renderer_paddle/rasterize.py
neural_renderer_paddle/renderer.py
neural_renderer_paddle/save_obj.py
neural_renderer_paddle/vertices_to_faces.py
neural_renderer_paddle/cuda/__init__.py
neural_renderer_paddle/cuda/create_texture_image.py
neural_renderer_paddle/cuda/create_texture_image_cuda.cc
neural_renderer_paddle/cuda/create_texture_image_cuda_kernel.cu
neural_renderer_paddle/cuda/load_textures.py
neural_renderer_paddle/cuda/load_textures_cuda.cc
neural_renderer_paddle/cuda/load_textures_cuda_kernel.cu
neural_renderer_paddle/cuda/rasterize.py
neural_renderer_paddle/cuda/rasterize_cuda.cc
neural_renderer_paddle/cuda/rasterize_cuda_kernel.cu
neural_renderer_paddle-1.1.3.4.dist-info/LICENSE
neural_renderer_paddle-1.1.3.4.dist-info/METADATA
neural_renderer_paddle-1.1.3.4.dist-info/WHEEL
neural_renderer_paddle-1.1.3.4.dist-info/top_level.txt
neural_renderer_paddle-1.1.3.4.dist-info/RECORD
