Metadata-Version: 2.1
Name: neural-renderer-paddle
Version: 1.1.3.4
Summary: PaddlePaddle implementation of "A 3D mesh renderer for neural networks"
Home-page: UNKNOWN
Author: Wu Hecong
Author-email: hecongw@gmail.com
License: MIT License
Platform: UNKNOWN
Requires-Dist: scikit-image (~=0.19.0)
Requires-Dist: paddlepaddle-gpu (~=2.2.0)
